mcp_pyautogui/__init__.py
mcp_pyautogui/main.py
mcp_pyautogui-0.0.4.dist-info/licenses/LICENSE
mcp_pyautogui-0.0.4.dist-info/METADATA
mcp_pyautogui-0.0.4.dist-info/WHEEL
mcp_pyautogui-0.0.4.dist-info/entry_points.txt
mcp_pyautogui-0.0.4.dist-info/top_level.txt
mcp_pyautogui-0.0.4.dist-info/RECORD
