Metadata-Version: 2.4
Name: mcp-pyautogui
Version: 0.0.4
Summary: A powerful MCP server for PyAutoGUI
Home-page: https://github.com/hathibelagal-dev/mcp-pyautogui
Author: Ashraff Hathibelagal
Project-URL: Source, https://github.com/hathibelagal-dev/mcp-pyautogui
Project-URL: Tracker, https://github.com/hathibelagal-dev/mcp-pyautogui/issues
Keywords: ai mcp claude llm llama pyautogui
Classifier: Development Status :: 4 - Beta
Classifier: Intended Audience :: Developers
Classifier: License :: OSI Approved :: GNU General Public License v3 (GPLv3)
Classifier: Programming Language :: Python :: 3.11
Classifier: Programming Language :: Python :: 3.12
Requires-Python: >=3.11
License-File: LICENSE
Requires-Dist: pyautogui
Requires-Dist: mcp
Dynamic: author
Dynamic: classifier
Dynamic: description
Dynamic: description-content-type
Dynamic: home-page
Dynamic: keywords
Dynamic: license-file
Dynamic: project-url
Dynamic: requires-dist
Dynamic: requires-python
Dynamic: summary
